ilovesyd/__init__.py
ilovesyd/api.py
ilovesyd-1.4.0.dist-info/METADATA
ilovesyd-1.4.0.dist-info/WHEEL
ilovesyd-1.4.0.dist-info/top_level.txt
ilovesyd-1.4.0.dist-info/RECORD
