Metadata-Version: 2.4
Name: ilovesyd
Version: 1.4.0
Summary: A Python wrapper for ilovesyd.xyz API
Home-page: https://github.com/KrishhVii/ilovesyd
Author: KrishVi
Author-email: KrishVi <krish@ilovesyd.xyz>
License: MIT
Project-URL: Homepage, https://github.com/KrishhVii/ilovesyd
Project-URL: Repository, https://github.com/KrishhVii/ilovesyd
Project-URL: Issues, https://github.com/KrishhVii/ilovesyd/issues
Requires-Python: >=3.7
Requires-Dist: requests
Dynamic: author
Dynamic: home-page
Dynamic: requires-python
